fastpapers/__init__.py
fastpapers/_nbdev.py
fastpapers/carion2020end.py
fastpapers/core.py
fastpapers/heusel2017gans.py
fastpapers/isola2017image.py
fastpapers/johnson2016perceptual.py
fastpapers/zhang2019self.py
fastpapers-0.0.8.dist-info/LICENSE
fastpapers-0.0.8.dist-info/METADATA
fastpapers-0.0.8.dist-info/WHEEL
fastpapers-0.0.8.dist-info/entry_points.txt
fastpapers-0.0.8.dist-info/top_level.txt
fastpapers-0.0.8.dist-info/RECORD
