Metadata-Version: 2.1
Name: fastpapers
Version: 0.0.8
Summary: Fastai implementation of papers.
Home-page: https://github.com/ababino/fastpapers/tree/master/
Author: Andres Babino
Author-email: ababino@gmail.com
License: Apache Software License 2.0
Keywords: fastai research ml vision nbdev
Platform: UNKNOWN
Classifier: Development Status :: 3 - Alpha
Classifier: Intended Audience :: Developers
Classifier: License :: OSI Approved :: Apache Software License
Classifier: Natural Language :: English
Classifier: Programming Language :: Python :: 3.6
Classifier: Programming Language :: Python :: 3.7
Classifier: Programming Language :: Python :: 3.8
Requires-Python: >=3.6
Requires-Dist: fastai (>=2.1.4)
Requires-Dist: fastcore
Requires-Dist: seaborn
Requires-Dist: pycocotools
Requires-Dist: torchfile
